robust_json/__init__.py
robust_json/core.py
robust_json_parser-0.1.6.dist-info/licenses/LICENSE
robust_json_parser-0.1.6.dist-info/METADATA
robust_json_parser-0.1.6.dist-info/WHEEL
robust_json_parser-0.1.6.dist-info/top_level.txt
robust_json_parser-0.1.6.dist-info/RECORD
