Metadata-Version: 2.4
Name: robust-json-parser
Version: 0.1.6
Summary: Robust JSON extraction and repair utilities for LLM-generated content.
Author-email: Derek <derek@preseen.ai>
Maintainer-email: Derek <derek@preseen.ai>
License-Expression: MIT
Project-URL: Homepage, https://github.com/callzhang/robust-json
Project-URL: Repository, https://github.com/callzhang/robust-json
Project-URL: Bug Tracker, https://github.com/callzhang/robust-json/issues
Project-URL: Documentation, https://github.com/callzhang/robust-json#readme
Keywords: json,llm,ai,validation,repair,parser,extraction,chatgpt,claude
Classifier: Development Status :: 4 - Beta
Classifier: Intended Audience :: Developers
Classifier: Topic :: Software Development :: Libraries :: Python Modules
Classifier: Topic :: Text Processing
Classifier: Topic :: Utilities
Classifier: Programming Language :: Python :: 3
Classifier: Programming Language :: Python :: 3.9
Classifier: Programming Language :: Python :: 3.10
Classifier: Programming Language :: Python :: 3.11
Classifier: Programming Language :: Python :: 3.12
Classifier: Programming Language :: Python :: 3 :: Only
Classifier: Operating System :: OS Independent
Classifier: Typing :: Typed
Requires-Python: >=3.9
License-File: LICENSE
Requires-Dist: typing-extensions>=4.0
Provides-Extra: speedups
Requires-Dist: numba>=0.58; extra == "speedups"
Provides-Extra: regex
Requires-Dist: regex>=2023.0.0; extra == "regex"
Provides-Extra: dev
Requires-Dist: pytest>=7.0; extra == "dev"
Requires-Dist: pytest-asyncio>=0.21; extra == "dev"
Requires-Dist: build>=0.10; extra == "dev"
Requires-Dist: twine>=4.0; extra == "dev"
Dynamic: license-file
